LICENSE.txt
MANIFEST.in
README.md
requirements.txt
setup.py
docs/conf.py
docs/theorems.txt
docs/changelog/0.0.1-changelog.txt
docs/changelog/0.0.2-changelog.txt
docs/changelog/0.0.3-changelog.txt
docs/changelog/0.1.0-changelog.txt
docs/changelog/0.1.1-changelog.txt
docs/changelog/0.2.0-changelog.txt
docs/changelog/0.2.1-changelog.txt
docs/changelog/0.2.10-changelog.txt
docs/changelog/0.2.11-changelog.txt
docs/changelog/0.2.12-changelog.txt
docs/changelog/0.2.13-changelog.txt
docs/changelog/0.2.2-changelog.txt
docs/changelog/0.2.3-changelog.txt
docs/changelog/0.2.4-changelog.txt
docs/changelog/0.2.5-changelog.txt
docs/changelog/0.2.6-changelog.txt
docs/changelog/0.2.7.changelog.txt
docs/changelog/0.2.8-changelog.txt
docs/changelog/0.2.9-changelog.txt
docs/changelog/0.3.0-changelog.txt
docs/changelog/0.3.1-changelog.txt
docs/changelog/1.0.0-changelog.txt
docs/changelog/1.0.1-changelog.txt
docs/changelog/1.1.0-changelog.txt
docs/changelog/1.1.1-changelog.txt
euclipy/__init__.py
euclipy/core.py
euclipy/exceptions.py
euclipy/geometricobjects.py
euclipy/polygon.py
euclipy/theorems.py
euclipy.egg-info/PKG-INFO
euclipy.egg-info/SOURCES.txt
euclipy.egg-info/dependency_links.txt
euclipy.egg-info/requires.txt
euclipy.egg-info/top_level.txt
tests/__init__.py
tests/test_object_framework.py
tests/test_proofs.py