Metadata-Version: 2.1
Name: euclipy
Version: 1.1.1
Summary: A Synthetic Euclidean Geometry based library
Home-page: 
Author: Joshua Varon
Author-email: 32440072+joshuavaron@users.noreply.github.com
License: MIT
Project-URL: Documentation, https://joshuavaron.github.io/euclipy/
Project-URL: Source Code, https://github.com/joshuavaron/euclipy
Keywords: geometry,math
Classifier: Development Status :: 5 - Production/Stable
Classifier: Intended Audience :: Education
Classifier: Operating System :: Microsoft :: Windows :: Windows 10
Classifier: License :: OSI Approved :: MIT License
Classifier: Programming Language :: Python :: 3
License-File: LICENSE.txt
Requires-Dist: sympy
